{
  "CallerReference": "sun-safety-frontend-20260316-1",
  "Comment": "HTTPS frontend for Sun Safety web app",
  "Enabled": true,
  "PriceClass": "PriceClass_100",
  "DefaultRootObject": "index.html",
  "Origins": {
    "Quantity": 1,
    "Items": [
      {
        "Id": "sun-safety-frontend-origin",
        "DomainName": "sun-safety-frontend-879161327720-20260316.s3-website-ap-southeast-2.amazonaws.com",
        "CustomOriginConfig": {
          "HTTPPort": 80,
          "HTTPSPort": 443,
          "OriginProtocolPolicy": "http-only",
          "OriginSslProtocols": {
            "Quantity": 1,
            "Items": ["TLSv1.2"]
          }
        }
      }
    ]
  },
  "DefaultCacheBehavior": {
    "TargetOriginId": "sun-safety-frontend-origin",
    "ViewerProtocolPolicy": "redirect-to-https",
    "AllowedMethods": {
      "Quantity": 2,
      "Items": ["GET", "HEAD"],
      "CachedMethods": {
        "Quantity": 2,
        "Items": ["GET", "HEAD"]
      }
    },
    "ForwardedValues": {
      "QueryString": false,
      "Cookies": {
        "Forward": "none"
      }
    },
    "MinTTL": 0,
    "DefaultTTL": 86400,
    "MaxTTL": 31536000
  },
  "CustomErrorResponses": {
    "Quantity": 2,
    "Items": [
      {
        "ErrorCode": 403,
        "ResponsePagePath": "/index.html",
        "ResponseCode": "200",
        "ErrorCachingMinTTL": 0
      },
      {
        "ErrorCode": 404,
        "ResponsePagePath": "/index.html",
        "ResponseCode": "200",
        "ErrorCachingMinTTL": 0
      }
    ]
  },
  "ViewerCertificate": {
    "CloudFrontDefaultCertificate": true
  }
}
